cytominer_database/__init__.py
cytominer_database/command.py
cytominer_database/ingest.py
cytominer_database/ingest_variable_engine.py
cytominer_database/load.py
cytominer_database/munge.py
cytominer_database/tableSchema.py
cytominer_database/utils.py
cytominer_database/write.py
cytominer_database/commands/__init__.py
cytominer_database/commands/command_ingest.py
cytominer_database/commands/command_ingest_variable_engine.py
cytominer_database/config/config_cellpainting.ini
cytominer_database/config/config_default.ini
cytominer_database/config/config_htqc.ini
cytominer_database/config/logging_config.json
cytominer_database-0.3.5.dist-info/LICENSE.md
cytominer_database-0.3.5.dist-info/METADATA
cytominer_database-0.3.5.dist-info/WHEEL
cytominer_database-0.3.5.dist-info/entry_points.txt
cytominer_database-0.3.5.dist-info/top_level.txt
cytominer_database-0.3.5.dist-info/RECORD
