Metadata-Version: 2.1
Name: cytominer-database
Version: 0.3.5
Summary: UNKNOWN
Home-page: https://github.com/cytomining/cytominer-database
Author: Shantanu Singh
Author-email: shsingh@broadinstitute.org
Maintainer: Gregory Way
Maintainer-email: gregory.way@gmail.com
License: BSD
Platform: UNKNOWN
Requires-Dist: click>=6.7
Requires-Dist: configparser>=3.5.0
Requires-Dist: csvkit<2,>=1.0.2
Requires-Dist: pandas>=0.20.3
Requires-Dist: pyarrow
